eeql/__init__.py
eeql/cli.py
eeql/utils.py
eeql/_vscode/__init__.py
eeql/_vscode/eeql-lsp-client.vsix
eeql/ast/__init__.py
eeql/ast/nodes.py
eeql/catalog/__init__.py
eeql/catalog/demo.py
eeql/catalog/interface.py
eeql/core/Aggregation.py
eeql/core/Attribute.py
eeql/core/Column.py
eeql/core/DataType.py
eeql/core/Dataset.py
eeql/core/DatasetColumn.py
eeql/core/DatasetEvent.py
eeql/core/Entity.py
eeql/core/Event.py
eeql/core/Filter.py
eeql/core/JoinType.py
eeql/core/Selector.py
eeql/core/__init__.py
eeql/engine/__init__.py
eeql/engine/compiler.py
eeql/engine/parser.py
eeql/engine/validator.py
eeql/grammar/eeql.lark
eeql/lsp/__init__.py
eeql/lsp/core.py
eeql/lsp/server.py
eeql/vocabulary/__init__.py
eeql/vocabulary/aggregations.py
eeql/vocabulary/attributes.py
eeql/vocabulary/data_types.py
eeql/vocabulary/derived_columns.py
eeql/vocabulary/join_types.py
eeql/vocabulary/selectors.py
eeql-0.3.0.dist-info/METADATA
eeql-0.3.0.dist-info/WHEEL
eeql-0.3.0.dist-info/entry_points.txt
eeql-0.3.0.dist-info/licenses/LICENSE
eeql-0.3.0.dist-info/RECORD
