Metadata-Version: 2.4
Name: eeql
Version: 0.3.0
Summary: EEQL (Event-Entity Query Language): a query language and Python toolkit for event-entity data models.
Project-URL: Homepage, https://github.com/daisydatahq/eeql
Project-URL: Repository, https://github.com/daisydatahq/eeql
Project-URL: Issues, https://github.com/daisydatahq/eeql/issues
Author-email: Bryce Codell <you@example.com>
License: Apache-2.0
License-File: LICENSE
Requires-Python: >=3.10
Requires-Dist: lark<2.0,>=1.1.9
Requires-Dist: networkx~=3.0
Requires-Dist: pydantic<3.0,>=2.0
Requires-Dist: pyyaml>=6.0.3
Requires-Dist: snowflake-connector-python<5.0.0,>=4.1.1
Requires-Dist: sqlglot<24,>=23
Provides-Extra: dev
Requires-Dist: pytest>=8.0.0; extra == 'dev'
Provides-Extra: http
Requires-Dist: fastapi>=0.110; extra == 'http'
Requires-Dist: uvicorn>=0.30; extra == 'http'
Provides-Extra: lsp
Requires-Dist: lsprotocol>=2023.0.0; extra == 'lsp'
Requires-Dist: pygls<3.0,>=2.0; extra == 'lsp'
